torch_levenberg_marquardt/__init__.py
torch_levenberg_marquardt/damping.py
torch_levenberg_marquardt/loss.py
torch_levenberg_marquardt/selection.py
torch_levenberg_marquardt/training.py
torch_levenberg_marquardt/tree.py
torch_levenberg_marquardt/utils.py
torch_levenberg_marquardt-1.2.2.dist-info/licenses/LICENSE
torch_levenberg_marquardt-1.2.2.dist-info/METADATA
torch_levenberg_marquardt-1.2.2.dist-info/WHEEL
torch_levenberg_marquardt-1.2.2.dist-info/top_level.txt
torch_levenberg_marquardt-1.2.2.dist-info/RECORD
