Metadata-Version: 2.4
Name: torch-levenberg-marquardt
Version: 1.2.2
Summary: PyTorch implementation of Levenberg-Marquardt training algorithm
Author-email: Fabio Di Marco <fabiodimarco@hotmail.it>
Maintainer-email: Fabio Di Marco <fabiodimarco@hotmail.it>
License: MIT License
Project-URL: Home-page, https://github.com/fabiodimarco/torch-levenberg-marquardt
Project-URL: Bug Reports, https://github.com/fabiodimarco/torch-levenberg-marquardt/issues
Project-URL: Source, https://github.com/fabiodimarco/torch-levenberg-marquardt/
Keywords: pytorch,optimization,levenberg-marquardt,gauss-newton,training,numerical optimization,nonlinear least squares,second-order methods
Classifier: Development Status :: 4 - Beta
Classifier: Intended Audience :: Developers
Classifier: Topic :: Scientific/Engineering :: Artificial Intelligence
Classifier: License :: OSI Approved :: MIT License
Classifier: Programming Language :: Python :: 3
Classifier: Programming Language :: Python :: 3.9
Classifier: Programming Language :: Python :: 3.10
Classifier: Programming Language :: Python :: 3.11
Requires-Python: >=3.9
License-File: LICENSE
Requires-Dist: torch>=2.0.0
Requires-Dist: numpy>=1.22
Requires-Dist: pytorch-lightning>=1.9
Requires-Dist: tqdm
Requires-Dist: torchmetrics>=0.11.0
Provides-Extra: dev
Requires-Dist: black; extra == "dev"
Requires-Dist: flake8; extra == "dev"
Requires-Dist: importlib_metadata; extra == "dev"
Provides-Extra: test
Requires-Dist: coverage; extra == "test"
Dynamic: license-file
